wyrdbound_rng/__init__.py
wyrdbound_rng/bayesian_model.py
wyrdbound_rng/cli.py
wyrdbound_rng/evaluator.py
wyrdbound_rng/exceptions.py
wyrdbound_rng/generated_name.py
wyrdbound_rng/generator.py
wyrdbound_rng/name.py
wyrdbound_rng/name_file_loader.py
wyrdbound_rng/name_list_resolver.py
wyrdbound_rng/statistics.py
wyrdbound_rng/syllable.py
wyrdbound_rng/syllable_stats.py
wyrdbound_rng/cache/__init__.py
wyrdbound_rng/cache/cache_adapter.py
wyrdbound_rng/cache/json_cache_adapter.py
wyrdbound_rng/data/generic-fantasy-female.yaml
wyrdbound_rng/data/generic-fantasy-male.yaml
wyrdbound_rng/data/generic-fantasy.yaml
wyrdbound_rng/data/japanese-sengoku-clan.yaml
wyrdbound_rng/data/japanese-sengoku-daimyo.yaml
wyrdbound_rng/data/japanese-sengoku-religious.yaml
wyrdbound_rng/data/japanese-sengoku-rogue.yaml
wyrdbound_rng/data/japanese-sengoku-samurai.yaml
wyrdbound_rng/data/japanese-sengoku-women.yaml
wyrdbound_rng/data/japanese-sengoku.yaml
wyrdbound_rng/data/japanese-swordsmen.yaml
wyrdbound_rng/data/warhammer40k-space-marine-names.yaml
wyrdbound_rng/segmenters/__init__.py
wyrdbound_rng/segmenters/fantasy_name_segmenter.py
wyrdbound_rng/segmenters/japanese_name_segmenter.py
wyrdbound_rng/segmenters/syllable_segmenter_base.py
wyrdbound_rng-0.0.1.dist-info/licenses/LICENSE
wyrdbound_rng-0.0.1.dist-info/METADATA
wyrdbound_rng-0.0.1.dist-info/WHEEL
wyrdbound_rng-0.0.1.dist-info/entry_points.txt
wyrdbound_rng-0.0.1.dist-info/top_level.txt
wyrdbound_rng-0.0.1.dist-info/RECORD
