Metadata-Version: 2.4
Name: wyrdbound-rng
Version: 0.0.1
Summary: A comprehensive random name generator library for tabletop RPGs
Author-email: The Wyrd One <wyrdbound@proton.me>
Maintainer-email: The Wyrd One <wyrdbound@proton.me>
License: MIT
Project-URL: Homepage, https://github.com/wyrdbound/wyrdbound-rng
Project-URL: Repository, https://github.com/wyrdbound/wyrdbound-rng
Project-URL: Documentation, https://github.com/wyrdbound/wyrdbound-rng#readme
Project-URL: Bug Tracker, https://github.com/wyrdbound/wyrdbound-rng/issues
Keywords: names,generator,random,tabletop,rpg,ttrpg,fantasy,procedural
Classifier: Development Status :: 5 - Production/Stable
Classifier: Intended Audience :: Developers
Classifier: Intended Audience :: End Users/Desktop
Classifier: Operating System :: OS Independent
Classifier: Programming Language :: Python :: 3
Classifier: Programming Language :: Python :: 3.8
Classifier: Programming Language :: Python :: 3.9
Classifier: Programming Language :: Python :: 3.10
Classifier: Programming Language :: Python :: 3.11
Classifier: Programming Language :: Python :: 3.12
Classifier: Topic :: Games/Entertainment :: Role-Playing
Classifier: Topic :: Software Development :: Libraries :: Python Modules
Classifier: Topic :: Text Processing :: Linguistic
Requires-Python: >=3.8
License-File: LICENSE
Requires-Dist: PyYAML>=6.0.0
Provides-Extra: dev
Requires-Dist: pytest>=7.0.0; extra == "dev"
Requires-Dist: pytest-cov>=4.0.0; extra == "dev"
Requires-Dist: ruff>=0.1.0; extra == "dev"
Requires-Dist: types-PyYAML>=6.0.0; extra == "dev"
Dynamic: license-file
